idf_build_apps/__init__.py
idf_build_apps/__main__.py
idf_build_apps/app.py
idf_build_apps/args.py
idf_build_apps/autocompletions.py
idf_build_apps/constants.py
idf_build_apps/finder.py
idf_build_apps/log.py
idf_build_apps/main.py
idf_build_apps/py.typed
idf_build_apps/session_args.py
idf_build_apps/utils.py
idf_build_apps/junit/__init__.py
idf_build_apps/junit/report.py
idf_build_apps/junit/utils.py
idf_build_apps/manifest/__init__.py
idf_build_apps/manifest/manifest.py
idf_build_apps/manifest/soc_header.py
idf_build_apps/vendors/__init__.py
idf_build_apps/vendors/pydantic_sources.py
idf_build_apps/yaml/__init__.py
idf_build_apps/yaml/parser.py
idf_build_apps-2.15.0.dist-info/entry_points.txt
idf_build_apps-2.15.0.dist-info/licenses/LICENSE
idf_build_apps-2.15.0.dist-info/WHEEL
idf_build_apps-2.15.0.dist-info/METADATA
idf_build_apps-2.15.0.dist-info/RECORD
