Metadata-Version: 2.4
Name: idf-build-apps
Version: 2.15.0
Summary: Tools for building ESP-IDF related apps.
Author-email: Fu Hanxi <fuhanxi@espressif.com>
Requires-Python: >=3.7
Classifier: Development Status :: 5 - Production/Stable
Classifier: License :: OSI Approved :: Apache Software License
Classifier: Programming Language :: Python :: 3.7
Classifier: Programming Language :: Python :: 3.8
Classifier: Programming Language :: Python :: 3.9
Classifier: Programming Language :: Python :: 3.10
Classifier: Programming Language :: Python :: 3.11
Classifier: Programming Language :: Python :: 3.12
Classifier: Programming Language :: Python :: 3.13
License-File: LICENSE
Requires-Dist: pyparsing
Requires-Dist: pyyaml
Requires-Dist: packaging
Requires-Dist: toml; python_version < '3.11'
Requires-Dist: pydantic~=2.0
Requires-Dist: pydantic_settings
Requires-Dist: argcomplete>=3
Requires-Dist: typing-extensions; python_version < '3.11'
Requires-Dist: esp-bool-parser>=0.1.2,<1
Requires-Dist: rich
Requires-Dist: sphinx ; extra == "doc"
Requires-Dist: sphinx-rtd-theme ; extra == "doc"
Requires-Dist: sphinx_copybutton ; extra == "doc"
Requires-Dist: myst-parser ; extra == "doc"
Requires-Dist: sphinxcontrib-mermaid ; extra == "doc"
Requires-Dist: sphinx-argparse ; extra == "doc"
Requires-Dist: sphinx-tabs ; extra == "doc"
Requires-Dist: pytest ; extra == "test"
Requires-Dist: pytest-cov ; extra == "test"
Project-URL: changelog, https://github.com/espressif/idf-build-apps/blob/main/CHANGELOG.md
Project-URL: documentation, https://docs.espressif.com/projects/idf-build-apps
Project-URL: homepage, https://github.com/espressif/idf-build-apps
Project-URL: repository, https://github.com/espressif/idf-build-apps
Provides-Extra: doc
Provides-Extra: test
